duke/__init__.py
duke/add_blender_command.py
duke/add_on_meta.py
duke/cli.py
duke/global_config.py
duke/new_command.py
duke/resources/__init__.py
duke/resources/unit_test_utility.py
duke/test_command.py
blender_duke-0.1.0.dist-info/entry_points.txt
blender_duke-0.1.0.dist-info/METADATA
blender_duke-0.1.0.dist-info/WHEEL
blender_duke-0.1.0.dist-info/RECORD
